[
  {
    "name": "Dmitro Govosyants",
    "position": "Team Lead",
    "image": "https://avatars.githubusercontent.com/u/91630215?v=4",
    "GitLink": "https://github.com/DmitriyGovosyants",
    "LinkedinLink": "https://www.linkedin.com/in/dmitro-govosyants-53b8a4156/"
  },
  {
    "name": "Maksym Pavlichenko",
    "position": "Scrum Master",
    "image": "https://avatars.githubusercontent.com/u/104983009?v=4",
    "GitLink": "https://github.com/MaksymPavlichenko",
    "LinkedinLink": "https://www.linkedin.com/in/maksym-pavlichenko-346b60191/"
  },
  {
    "name": "Nikita Durnev",
    "position": "Main Developer",
    "image": "https://avatars.githubusercontent.com/u/92080056?v=4",
    "GitLink": "https://github.com/NickDurnev",
    "LinkedinLink": "https://www.linkedin.com/in/nikita-durnev-2291b3244/"
  },
    {
    "name": "Mykhailo Kuzich",
    "position": "Main FE Developer",
    "image": "https://avatars.githubusercontent.com/u/97763883?v=4",
    "GitLink": "https://github.com/MKuzich",
    "LinkedinLink": "https://www.linkedin.com/in/mykhailo-kuzich/"
  },
  {
    "name": "Ihor Melnyk",
    "position": "FE Developer",
    "image": "https://avatars.githubusercontent.com/u/92684157?v=4",
    "GitLink": "https://github.com/Ihor-Melnyk",
    "LinkedinLink": "https://www.linkedin.com/in/ihor-melnyk/"
  },
  {
    "name": "Oleh Kulyk",
    "position": "FE Developer",
    "image": "https://avatars.githubusercontent.com/u/92692410?v=4",
    "GitLink": "https://github.com/OlehKulyk2710",
    "LinkedinLink": "https://www.linkedin.com/in/oleh-kulyk-79a2b8a9/"
  },
  {
    "name": "Viktor Tytenko",
    "position": "FE Developer",
    "image": "https://avatars.githubusercontent.com/u/92685344?v=4",
    "GitLink": "https://github.com/ViktorTyt",
    "LinkedinLink": "https://www.linkedin.com/in/viktor-tytenko/"
  },
  {
    "name": "Max Vidomenko",
    "position": "FE Developer",
    "image": "https://avatars.githubusercontent.com/u/92626684?v=4",
    "GitLink": "https://github.com/MaxVidom",
    "LinkedinLink": "https://www.linkedin.com/in/max-vidom/"
  },
  {
    "name": "Snizhana Tkachuk",
    "position": "FE Developer",
    "image": "https://avatars.githubusercontent.com/u/92599234?v=4",
    "GitLink": "https://github.com/Snizhana15",
    "LinkedinLink": "https://www.linkedin.com/in/snizhana-tkachuk-655b1719a"
  },
  {
    "name": "Vladimir Pavlov",
    "position": "FE Developer",
    "image": "https://avatars.githubusercontent.com/u/91782115?v=4",
    "GitLink": "https://github.com/Popeye80",
    "LinkedinLink": "https://linkedin.com/in/pavlovvladimir"
  },
  {
    "name": "Oleksandr Bragynator",
    "position": "FE Developer",
    "image": "https://avatars.githubusercontent.com/u/92689909?v=4",
    "GitLink": "https://github.com/bragynator",
    "LinkedinLink": "https://www.linkedin.com/in/"
  },
  {
    "name": "Yurij Kovbasyuk",
    "position": "BE Developer",
    "image": "https://avatars.githubusercontent.com/u/93015127?v=4",
    "GitLink": "https://github.com/YurijKovbasyuk",
    "LinkedinLink": "https://www.linkedin.com/in/yurijkovbasyuk/"
  },
  {
    "name": "Maxim Stribaylo",
    "position": "BE Developer",
    "image": "https://avatars.githubusercontent.com/u/91918033?v=4",
    "GitLink": "https://github.com/Maxstr75",
    "LinkedinLink": "http://linkedin.com/in/maxim-strybailo"
  }
]
